e3lm/__init__.py
e3lm/cli.py
e3lm/contrib/__init__.py
e3lm/contrib/dot.py
e3lm/contrib/json.py
e3lm/contrib/units.py
e3lm/demos/__init__.py
e3lm/demos/data.py
e3lm/helpers/__init__.py
e3lm/helpers/printers.py
e3lm/lang/__init__.py
e3lm/lang/ast.py
e3lm/lang/data.py
e3lm/lang/interpreters.py
e3lm/lang/lexer.py
e3lm/lang/parser.py
e3lm/lang/parsetab.py
e3lm/tests/__init__.py
e3lm/tests/test_contrib.py
e3lm/tests/test_interpreters.py
e3lm/tests/test_lexer.py
e3lm/tests/test_parser.py
e3lm/tests/test_utils.py
e3lm/utils/__init__.py
e3lm/utils/funcs.py
e3lm/utils/lang.py
e3lm/utils/spin.py
e3lm-0.1.9.dist-info/LICENSE
e3lm-0.1.9.dist-info/METADATA
e3lm-0.1.9.dist-info/WHEEL
e3lm-0.1.9.dist-info/entry_points.txt
e3lm-0.1.9.dist-info/top_level.txt
e3lm-0.1.9.dist-info/RECORD
