Metadata-Version: 2.1
Name: e3lm
Version: 0.1.9
Summary: e3lm CLI tool (3lm language) for managing .3lm projects and files.
Home-page: https://github.com/knno/3lm
Author: Kenan Masri
Author-email: kenanmasri@outlook.com
Project-URL: Bug Tracker, https://github.com/knno/3lm/issues
Classifier: Programming Language :: Python :: 3
Classifier: License :: OSI Approved :: MIT License
Classifier: Operating System :: OS Independent
Requires-Python: >=3.8
License-File: LICENSE
Requires-Dist: ansicolors
Requires-Dist: asciitree
Requires-Dist: attrs
Requires-Dist: graphviz
Requires-Dist: charset-normalizer
Requires-Dist: colorama
Requires-Dist: iniconfig
Requires-Dist: jinja2
Requires-Dist: markupsafe
Requires-Dist: more-itertools
Requires-Dist: packaging
Requires-Dist: pillow
Requires-Dist: pluggy
Requires-Dist: ply
Requires-Dist: py
Requires-Dist: pycodestyle
Requires-Dist: pyparsing
Requires-Dist: six
Requires-Dist: toml
Requires-Dist: tomli
Requires-Dist: untokenize
